{
  "main": {
    "id": "21b8cd3f4d6a6f93",
    "type": "split",
    "children": [
      {
        "id": "5742c2309f25a9d9",
        "type": "tabs",
        "children": [
          {
            "id": "692e3b76c9f59e36",
            "type": "leaf",
            "state": {
              "type": "markdown",
              "state": {
                "file": "database/redis/docker-redis.md",
                "mode": "source",
                "backlinks": false,
                "source": false
              }
            }
          }
        ]
      }
    ],
    "direction": "vertical"
  },
  "left": {
    "id": "d619e0ae4b052a14",
    "type": "split",
    "children": [
      {
        "id": "35cf54de3708f806",
        "type": "tabs",
        "children": [
          {
            "id": "1c87ef4150171b05",
            "type": "leaf",
            "state": {
              "type": "file-explorer",
              "state": {
                "sortOrder": "alphabetical"
              }
            }
          },
          {
            "id": "b7b371eec0b4f14f",
            "type": "leaf",
            "state": {
              "type": "search",
              "state": {
                "query": "tag:#事务操作",
                "matchingCase": false,
                "explainSearch": false,
                "collapseAll": false,
                "extraContext": false,
                "sortOrder": "alphabetical"
              }
            }
          },
          {
            "id": "d9ea98599d18ffe4",
            "type": "leaf",
            "state": {
              "type": "bookmarks",
              "state": {}
            }
          }
        ]
      }
    ],
    "direction": "horizontal",
    "width": 200
  },
  "right": {
    "id": "85c594c4de743e1c",
    "type": "split",
    "children": [
      {
        "id": "989c066559de81d5",
        "type": "tabs",
        "dimension": 57.986111111111114,
        "children": [
          {
            "id": "cba9d319529b09a9",
            "type": "leaf",
            "state": {
              "type": "outline",
              "state": {
                "file": "database/redis/docker-redis.md"
              }
            }
          }
        ]
      },
      {
        "id": "fe7f13f242f3f5d9",
        "type": "tabs",
        "dimension": 42.01388888888889,
        "children": [
          {
            "id": "4452de32859f1fef",
            "type": "leaf",
            "state": {
              "type": "git-view",
              "state": {}
            }
          },
          {
            "id": "c955ecc64b9c3a9f",
            "type": "leaf",
            "state": {
              "type": "git-history-view",
              "state": {}
            }
          }
        ]
      }
    ],
    "direction": "horizontal",
    "width": 300.5
  },
  "left-ribbon": {
    "hiddenItems": {
      "switcher:打开快速切换": false,
      "graph:查看关系图谱": false,
      "command-palette:打开命令面板": false,
      "canvas:新建白板": false
    }
  },
  "active": "692e3b76c9f59e36",
  "lastOpenFiles": [
    "未命名.canvas",
    "database/redis/docker-redis.md",
    "java/springboot/mybatis.md",
    "docker/install.md",
    "docker/services.md",
    "docker/Dockerfile.md",
    "design-mode/facade(外观模式).md",
    "design-mode/adapter.md",
    "regular/1.md",
    "java/springboot/data-format.md",
    "java/springboot/images/Pasted image 20240313134557.png",
    "java",
    "database/redis/持久化.md",
    "linux/防火墙.md",
    "linux/命令分隔符.md",
    "linux/ifcfg-enc33.md",
    "linux/systemctl.md",
    "readme.md",
    "java/springboot/global-exception-handler.md",
    "[Install.md",
    "java/springboot/images",
    "database/mysql/user and authority.md",
    "database/redis/install.md",
    "database/mysql/sql.md",
    "database/redis/redis事务.md",
    "database/redis/命令.md",
    "database/redis/主从复制和哨兵.md",
    "java/jvm",
    "database/mysql/images/Pasted image 20240312190927.png",
    "database/mysql/install.md",
    "database/mysql/索引index.md",
    "design-mode",
    "database/mysql/images/Pasted image 20240224171031.png",
    "database/mysql/images/Pasted image 20240224163936.png",
    "database/mysql/images/Pasted image 20240224161541.png",
    "database/mysql/images/Pasted image 20240224151215.png",
    "database/mysql/images/Pasted image 20240224150709.png",
    "database/mysql/images/Pasted image 20240224150642.png",
    "database/mysql/images/Pasted image 20240224150508.png",
    "database/mysql/images/Pasted image 20240224150441.png",
    "images",
    "database/mysql/images",
    "frp",
    "database/elasticsearch",
    "springboot/mybatis",
    "java/springboot",
    "qqq.canvas",
    "bzd.canvas",
    "未命名 2.canvas",
    "未命名 3.canvas",
    "未命名 1.canvas"
  ]
}